pretrained_word_embedding/__init__.py
pretrained_word_embedding/pretrained_word_embedding.py
pretrained_word_embedding-0.0.2.dist-info/METADATA
pretrained_word_embedding-0.0.2.dist-info/WHEEL
pretrained_word_embedding-0.0.2.dist-info/top_level.txt
pretrained_word_embedding-0.0.2.dist-info/RECORD
