Metadata-Version: 2.1
Name: pretrained-word-embedding
Version: 0.0.2
Summary: packages that load pretrained word embeddings
Home-page: https://github.com/yunshu67/pretrained-word-embedding
Author: Tao Xiang
Author-email: tao.xiang@tum.de
License: UNKNOWN
Platform: UNKNOWN
Classifier: Programming Language :: Python :: 3
Classifier: License :: OSI Approved :: GNU General Public License v3 (GPLv3)
Classifier: Operating System :: OS Independent
Requires-Python: >=3.6
